geektime_dl/__init__.py
geektime_dl/cli/__init__.py
geektime_dl/cli/command.py
geektime_dl/cli/dailylesson.py
geektime_dl/cli/ebook.py
geektime_dl/cli/login.py
geektime_dl/cli/mp3.py
geektime_dl/cli/mp4.py
geektime_dl/cli/query.py
geektime_dl/data_client/__init__.py
geektime_dl/data_client/gk_apis.py
geektime_dl/utils/__init__.py
geektime_dl/utils/ebook.py
geektime_dl/utils/log.py
geektime_dl/utils/m3u8_downloader.py
geektime_dl/utils/mail.py
geektime_dl/utils/mp3_downloader.py
geektime_dl/utils/templates/article.html
geektime_dl-1.1.2.dist-info/METADATA
geektime_dl-1.1.2.dist-info/WHEEL
geektime_dl-1.1.2.dist-info/entry_points.txt
geektime_dl-1.1.2.dist-info/top_level.txt
geektime_dl-1.1.2.dist-info/RECORD
