Metadata-Version: 2.1
Name: geektime-dl
Version: 1.1.2
Summary: 把极客时间装进 Kindle
Home-page: https://jachinlin.github.io/geektime_dl
Author: jachinlin
Author-email: linjx1000+github@gmail.com
License: MIT
Keywords: kindle ebook mobi geektime
Platform: UNKNOWN
Classifier: Programming Language :: Python
Classifier: Programming Language :: Python :: 3
Classifier: Programming Language :: Python :: 3.5
Classifier: Programming Language :: Python :: 3.6
Classifier: Programming Language :: Python :: 3.7
Classifier: Programming Language :: Python :: 3 :: Only
Requires-Dist: kindle-maker
Requires-Dist: requests
Requires-Dist: tinydb
Requires-Dist: termcolor
Requires-Dist: tqdm
Requires-Dist: pillow
